[
  {
    "ean": "0619659125974",
    "asin": "B00YFI1A66",
    "name": "SanDisk Ultra USB 3.0",
    "supplier_cost": 18.3,
    "amazon_price": 40.99,
    "fees": 10.22,
    "profit": 12.470000000000002,
    "roi": 68.14207650273225,
    "estimated_sales": 334,
    "amazon_link": "https://www.amazon.fr/dp/B00YFI1A66",
    "supplier_link": "https://www.idealo.fr/prix/4799169/sandisk-ultra-usb-3-0-256-go.html",
    "sas_link": "https://sas.selleramp.com/sas/lookup?SasLookup%5Bsearch_term%5D=B00YFI1A66",
    "image_url": "https://m.media-amazon.com/images/I/315vLm4T1OL._SL120_.jpg",
    "posted": false,
    "posted_at": null,
    "created_at": "2026-07-23T06:28:18.589810+00:00"
  },
  {
    "ean": "8806097640233",
    "asin": "B0FT1WD866",
    "name": "Samsung Galaxy A17 5G",
    "supplier_cost": 193.05599999999998,
    "amazon_price": 272.49,
    "fees": 24.24,
    "profit": 55.19400000000002,
    "roi": 28.589632023868734,
    "estimated_sales": 47,
    "amazon_link": "https://www.amazon.fr/dp/B0FT1WD866",
    "supplier_link": "https://www.idealo.fr/prix/207240141/samsung-galaxy-a17-5g-8-go-256-go-bleu.html",
    "sas_link": "https://sas.selleramp.com/sas/lookup?SasLookup%5Bsearch_term%5D=B0FT1WD866",
    "image_url": "https://m.media-amazon.com/images/I/41JyMhVFjhL._SL120_.jpg",
    "posted": false,
    "posted_at": null,
    "created_at": "2026-07-23T06:28:22.731313+00:00"
  },
  {
    "ean": "0649528903624",
    "asin": "B08C56GZGK",
    "name": "Crucial 16 Go DDR4-3200 CL22 (CT16G4DFRA32A)",
    "supplier_cost": 86.58,
    "amazon_price": 143.0,
    "fees": 14.21,
    "profit": 42.209999999999994,
    "roi": 48.75259875259875,
    "estimated_sales": 265,
    "amazon_link": "https://www.amazon.fr/dp/B08C56GZGK",
    "supplier_link": "https://www.idealo.fr/prix/200568640/crucial-16-go-ddr4-3200-cl22-ct16g4dfra32a.html",
    "sas_link": "https://sas.selleramp.com/sas/lookup?SasLookup%5Bsearch_term%5D=B08C56GZGK",
    "image_url": "https://m.media-amazon.com/images/I/41uzS4+-ZRL._SL120_.jpg",
    "posted": false,
    "posted_at": null,
    "created_at": "2026-07-23T06:28:29.181760+00:00"
  },
  {
    "ean": "0858511001128",
    "asin": "B0961ZS96M",
    "name": "K18 Leave-In Molecular Repair Hair Mask",
    "supplier_cost": 23.976,
    "amazon_price": 64.38,
    "fees": 15.91,
    "profit": 24.494,
    "roi": 102.16049382716051,
    "estimated_sales": 253,
    "amazon_link": "https://www.amazon.fr/dp/B0961ZS96M",
    "supplier_link": "https://www.idealo.fr/prix/201201891/k18-leave-in-molecular-repair-hair-mask-50-ml.html",
    "sas_link": "https://sas.selleramp.com/sas/lookup?SasLookup%5Bsearch_term%5D=B0961ZS96M",
    "image_url": "https://m.media-amazon.com/images/I/51BuwTsdTeL._SL120_.jpg",
    "posted": false,
    "posted_at": null,
    "created_at": "2026-07-23T06:28:32.747087+00:00"
  },
  {
    "ean": "0740617326154",
    "asin": "B09T95TJ1M",
    "name": "Kingston FURY Impact 16 Go DDR5-4800 CL38 (KF548S38IB-16)",
    "supplier_cost": 91.45199999999998,
    "amazon_price": 215.71,
    "fees": 19.45,
    "profit": 104.80800000000004,
    "roi": 114.60438262695189,
    "estimated_sales": 68,
    "amazon_link": "https://www.amazon.fr/dp/B09T95TJ1M",
    "supplier_link": "https://www.idealo.fr/prix/201989967/kingston-fury-impact-16-go-ddr5-4800-cl38-kf548s38ib-16.html",
    "sas_link": "https://sas.selleramp.com/sas/lookup?SasLookup%5Bsearch_term%5D=B09T95TJ1M",
    "image_url": "https://m.media-amazon.com/images/I/317J2yiOpwL._SL120_.jpg",
    "posted": false,
    "posted_at": null,
    "created_at": "2026-07-23T06:29:12.370112+00:00"
  },
  {
    "ean": "0725882062525",
    "asin": "B0BJVQ5TBX",
    "name": "Polar Ignite 3",
    "supplier_cost": 135.612,
    "amazon_price": 212.0,
    "fees": 21.73,
    "profit": 54.658000000000015,
    "roi": 40.304692800047206,
    "estimated_sales": 40,
    "amazon_link": "https://www.amazon.fr/dp/B0BJVQ5TBX",
    "supplier_link": "https://www.idealo.fr/prix/202216815/polar-ignite-3-marron.html",
    "sas_link": "https://sas.selleramp.com/sas/lookup?SasLookup%5Bsearch_term%5D=B0BJVQ5TBX",
    "image_url": "https://m.media-amazon.com/images/I/41Au7Wz9rFL._SL120_.jpg",
    "posted": false,
    "posted_at": null,
    "created_at": "2026-07-23T06:29:24.068899+00:00"
  },
  {
    "ean": "0846504003662",
    "asin": "B07X5MMGWG",
    "name": "Synology 4 Go SODIMM DDR4-2666 (D4NESO-2666-4G)",
    "supplier_cost": 65.688,
    "amazon_price": 163.4,
    "fees": 24.57,
    "profit": 73.14200000000001,
    "roi": 111.3475825112654,
    "estimated_sales": 5,
    "amazon_link": "https://www.amazon.fr/dp/B07X5MMGWG",
    "supplier_link": "https://www.idealo.fr/prix/200382966/synology-4-go-sodimm-ddr4-2666-d4neso-2666-4g.html",
    "sas_link": "https://sas.selleramp.com/sas/lookup?SasLookup%5Bsearch_term%5D=B07X5MMGWG",
    "image_url": "https://m.media-amazon.com/images/I/41CxFXk6BPL._SL120_.jpg",
    "posted": false,
    "posted_at": null,
    "created_at": "2026-07-23T06:29:27.089277+00:00"
  },
  {
    "ean": "4713218469199",
    "asin": "B07KQXC7KR",
    "name": "ADATA Ultimate SU630 960 Go",
    "supplier_cost": 112.74,
    "amazon_price": 175.94,
    "fees": 16.61,
    "profit": 46.58999999999999,
    "roi": 41.32517296434273,
    "estimated_sales": 20,
    "amazon_link": "https://www.amazon.fr/dp/B07KQXC7KR",
    "supplier_link": "https://www.idealo.fr/prix/6779489/adata-ultimate-su630-960-go.html",
    "sas_link": "https://sas.selleramp.com/sas/lookup?SasLookup%5Bsearch_term%5D=B07KQXC7KR",
    "image_url": "https://m.media-amazon.com/images/I/31y9OhhdueL._SL120_.jpg",
    "posted": false,
    "posted_at": null,
    "created_at": "2026-07-23T06:31:22.157054+00:00"
  },
  {
    "ean": "6924328320661",
    "asin": "B07LFWY9FB",
    "name": "Worx Landroid M700",
    "supplier_cost": 461.856,
    "amazon_price": 735.66,
    "fees": 128.25,
    "profit": 145.55399999999997,
    "roi": 31.515017667844518,
    "estimated_sales": 94,
    "amazon_link": "https://www.amazon.fr/dp/B07LFWY9FB",
    "supplier_link": "https://www.idealo.fr/prix/202040628/worx-landroid-m700-2022.html",
    "sas_link": "https://sas.selleramp.com/sas/lookup?SasLookup%5Bsearch_term%5D=B07LFWY9FB",
    "image_url": "https://m.media-amazon.com/images/I/41-j2m18DsL._SL120_.jpg",
    "posted": false,
    "posted_at": null,
    "created_at": "2026-07-23T06:32:45.469053+00:00"
  },
  {
    "ean": "0195161213915",
    "asin": "B08WJDJQCZ",
    "name": "HP OfficeJet Pro 9012e (22A55B)",
    "supplier_cost": 219.828,
    "amazon_price": 550.0,
    "fees": 52.59,
    "profit": 277.582,
    "roi": 126.27235838928617,
    "estimated_sales": 94,
    "amazon_link": "https://www.amazon.fr/dp/B08WJDJQCZ",
    "supplier_link": "https://www.idealo.fr/prix/201300215/hp-officejet-pro-9012e-22a55b.html",
    "sas_link": "https://sas.selleramp.com/sas/lookup?SasLookup%5Bsearch_term%5D=B08WJDJQCZ",
    "image_url": "https://m.media-amazon.com/images/I/31pIvz1SUBL._SL120_.jpg",
    "posted": false,
    "posted_at": null,
    "created_at": "2026-07-23T06:33:56.407960+00:00"
  },
  {
    "ean": "0740617300253",
    "asin": "B07ZDBT15M",
    "name": "Kingston KC600 512 Go",
    "supplier_cost": 116.68799999999999,
    "amazon_price": 164.49,
    "fees": 15.76,
    "profit": 32.04200000000003,
    "roi": 27.45955025366793,
    "estimated_sales": 6,
    "amazon_link": "https://www.amazon.fr/dp/B07ZDBT15M",
    "supplier_link": "https://www.idealo.fr/prix/6844086/kingston-kc600-512-go.html",
    "sas_link": "https://sas.selleramp.com/sas/lookup?SasLookup%5Bsearch_term%5D=B07ZDBT15M",
    "image_url": "https://m.media-amazon.com/images/I/31DFVnY5YML._SL120_.jpg",
    "posted": false,
    "posted_at": null,
    "created_at": "2026-07-23T06:34:52.619718+00:00"
  },
  {
    "ean": "0195019487314",
    "asin": "B0BMM7BWW1",
    "name": "Merrell Moab 3 GTX",
    "supplier_cost": 90.24,
    "amazon_price": 160.0,
    "fees": 32.71,
    "profit": 37.05,
    "roi": 41.057180851063826,
    "estimated_sales": 104,
    "amazon_link": "https://www.amazon.fr/dp/B0BMM7BWW1",
    "supplier_link": "https://www.idealo.fr/prix/203193049/merrell-moab-3-gtx-navy-navy.html",
    "sas_link": "https://sas.selleramp.com/sas/lookup?SasLookup%5Bsearch_term%5D=B0BMM7BWW1",
    "image_url": "https://m.media-amazon.com/images/I/41su1L+1OBL._SL120_.jpg",
    "posted": false,
    "posted_at": null,
    "created_at": "2026-07-23T06:36:04.035145+00:00"
  },
  {
    "ean": "3126170170231",
    "asin": "B07XVRYYV1",
    "name": "Emtec X200 Portable Power Plus",
    "supplier_cost": 43.632,
    "amazon_price": 76.87,
    "fees": 11.16,
    "profit": 22.07800000000001,
    "roi": 50.60047671433813,
    "estimated_sales": 24,
    "amazon_link": "https://www.amazon.fr/dp/B07XVRYYV1",
    "supplier_link": "https://www.idealo.fr/prix/6791235/emtec-x200-portable-power-plus-256-go.html",
    "sas_link": "https://sas.selleramp.com/sas/lookup?SasLookup%5Bsearch_term%5D=B07XVRYYV1",
    "image_url": "https://m.media-amazon.com/images/I/31LkXG3qY0L._SL120_.jpg",
    "posted": false,
    "posted_at": null,
    "created_at": "2026-07-23T06:36:33.150486+00:00"
  },
  {
    "ean": "0814914026915",
    "asin": "B0865SG2SW",
    "name": "Patriot Viper Steel 32 Go DDR4-3600 CL18 (PVS432G360C8)",
    "supplier_cost": 159.468,
    "amazon_price": 299.99,
    "fees": 36.4,
    "profit": 104.12200000000004,
    "roi": 65.29335039004694,
    "estimated_sales": 258,
    "amazon_link": "https://www.amazon.fr/dp/B0865SG2SW",
    "supplier_link": "https://www.idealo.fr/prix/200295260/patriot-viper-steel-32-go-ddr4-3600-cl18-pvs432g360c8.html",
    "sas_link": "https://sas.selleramp.com/sas/lookup?SasLookup%5Bsearch_term%5D=B0865SG2SW",
    "image_url": "https://m.media-amazon.com/images/I/41voPGvS+-L._SL120_.jpg",
    "posted": false,
    "posted_at": null,
    "created_at": "2026-07-23T06:38:52.554576+00:00"
  },
  {
    "ean": "0740617337976",
    "asin": "B0CGLW3GWG",
    "name": "Kingston FURY Beast RGB 16GB DDR4-3200 CL16 (KF432C16BB12A/16)",
    "supplier_cost": 71.976,
    "amazon_price": 178.5,
    "fees": 17.34,
    "profit": 89.184,
    "roi": 123.90796932310771,
    "estimated_sales": 60,
    "amazon_link": "https://www.amazon.fr/dp/B0CGLW3GWG",
    "supplier_link": "https://www.idealo.fr/prix/203565251/kingston-fury-beast-rgb-16gb-ddr4-3200-cl16-kf432c16bb12a-16.html",
    "sas_link": "https://sas.selleramp.com/sas/lookup?SasLookup%5Bsearch_term%5D=B0CGLW3GWG",
    "image_url": "https://m.media-amazon.com/images/I/31FE+829i3L._SL120_.jpg",
    "posted": false,
    "posted_at": null,
    "created_at": "2026-07-23T06:38:53.485418+00:00"
  },
  {
    "ean": "0740617337426",
    "asin": "B0CGLVPCCK",
    "name": "Kingston FURY Beast RGB 16GB DDR4-3600 CL18 (KF436C18BB2A/16)",
    "supplier_cost": 79.176,
    "amazon_price": 207.29,
    "fees": 28.76,
    "profit": 99.354,
    "roi": 125.48499545316763,
    "estimated_sales": 60,
    "amazon_link": "https://www.amazon.fr/dp/B0CGLVPCCK",
    "supplier_link": "https://www.idealo.fr/prix/203565880/kingston-fury-beast-rgb-16gb-ddr4-3600-cl18-kf436c18bb2a-16.html",
    "sas_link": "https://sas.selleramp.com/sas/lookup?SasLookup%5Bsearch_term%5D=B0CGLVPCCK",
    "image_url": "https://m.media-amazon.com/images/I/31FE+829i3L._SL120_.jpg",
    "posted": false,
    "posted_at": null,
    "created_at": "2026-07-23T06:38:54.706680+00:00"
  },
  {
    "ean": "0740617324402",
    "asin": "B09K7CR37G",
    "name": "Kingston KC3000",
    "supplier_cost": 98.376,
    "amazon_price": 150.03,
    "fees": 14.74,
    "profit": 36.91399999999999,
    "roi": 37.52337968610229,
    "estimated_sales": 108,
    "amazon_link": "https://www.amazon.fr/dp/B09K7CR37G",
    "supplier_link": "https://www.idealo.fr/prix/201679558/kingston-kc3000-512-go.html",
    "sas_link": "https://sas.selleramp.com/sas/lookup?SasLookup%5Bsearch_term%5D=B09K7CR37G",
    "image_url": "https://m.media-amazon.com/images/I/31p3IUZV+ZL._SL120_.jpg",
    "posted": false,
    "posted_at": null,
    "created_at": "2026-07-23T06:38:56.053296+00:00"
  },
  {
    "ean": "0740617335019",
    "asin": "B0BXBBCYLQ",
    "name": "Kingston 8 Go DDR5-5600 CL46 (KCP556SS6-8)",
    "supplier_cost": 77.736,
    "amazon_price": 173.29,
    "fees": 25.38,
    "profit": 70.17399999999999,
    "roi": 90.27220335494492,
    "estimated_sales": 62,
    "amazon_link": "https://www.amazon.fr/dp/B0BXBBCYLQ",
    "supplier_link": "https://www.idealo.fr/prix/202666952/kingston-8-go-ddr5-5600-cl46-kcp556ss6-8.html",
    "sas_link": "https://sas.selleramp.com/sas/lookup?SasLookup%5Bsearch_term%5D=B0BXBBCYLQ",
    "image_url": "https://m.media-amazon.com/images/I/21HUJ84dJxL._SL120_.jpg",
    "posted": false,
    "posted_at": null,
    "created_at": "2026-07-23T06:39:01.105451+00:00"
  },
  {
    "ean": "0740617331752",
    "asin": "B0BRTK24SY",
    "name": "Kingston FURY Beast 32 Go DDR5-5600 CL36",
    "supplier_cost": 191.72400000000002,
    "amazon_price": 404.99,
    "fees": 44.5,
    "profit": 168.766,
    "roi": 88.02549498237047,
    "estimated_sales": 162,
    "amazon_link": "https://www.amazon.fr/dp/B0BRTK24SY",
    "supplier_link": "https://www.idealo.fr/prix/202293337/kingston-fury-beast-32-go-ddr5-5600-cl36-kf556c36bbe-32.html",
    "sas_link": "https://sas.selleramp.com/sas/lookup?SasLookup%5Bsearch_term%5D=B0BRTK24SY",
    "image_url": "https://m.media-amazon.com/images/I/31UWHrJgKoL._SL120_.jpg",
    "posted": false,
    "posted_at": null,
    "created_at": "2026-07-23T06:39:06.512304+00:00"
  },
  {
    "ean": "0718037884684",
    "asin": "B0CFLSHNL3",
    "name": "Western Digital Blue SA510",
    "supplier_cost": 231.816,
    "amazon_price": 349.0,
    "fees": 29.09,
    "profit": 88.09400000000002,
    "roi": 38.001690996307424,
    "estimated_sales": 19,
    "amazon_link": "https://www.amazon.fr/dp/B0CFLSHNL3",
    "supplier_link": "https://www.idealo.fr/prix/203330333/western-digital-blue-sa510-2tb-m-2.html",
    "sas_link": "https://sas.selleramp.com/sas/lookup?SasLookup%5Bsearch_term%5D=B0CFLSHNL3",
    "image_url": "https://m.media-amazon.com/images/I/3127OjxAEiL._SL120_.jpg",
    "posted": false,
    "posted_at": null,
    "created_at": "2026-07-23T06:39:08.031081+00:00"
  },
  {
    "ean": "4063699638134",
    "asin": "B08MT38VYC",
    "name": "Puma Smash v2 L",
    "supplier_cost": 30.887999999999998,
    "amazon_price": 67.51,
    "fees": 17.43,
    "profit": 19.192000000000007,
    "roi": 62.13416213416216,
    "estimated_sales": 124,
    "amazon_link": "https://www.amazon.fr/dp/B08MT38VYC",
    "supplier_link": "https://www.idealo.fr/prix/201964350/puma-smash-v2-l-puma-white-puma-white-peacoat-puma-team-gold.html",
    "sas_link": "https://sas.selleramp.com/sas/lookup?SasLookup%5Bsearch_term%5D=B08MT38VYC",
    "image_url": "https://m.media-amazon.com/images/I/31+bT+eYCwL._SL120_.jpg",
    "posted": false,
    "posted_at": null,
    "created_at": "2026-07-23T06:39:58.757399+00:00"
  },
  {
    "ean": "0718037872384",
    "asin": "B07YFG3R5N",
    "name": "Western Digital Red SA500 1 To 2.5",
    "supplier_cost": 163.752,
    "amazon_price": 290.99,
    "fees": 24.91,
    "profit": 102.32799999999997,
    "roi": 62.489618447408255,
    "estimated_sales": 42,
    "amazon_link": "https://www.amazon.fr/dp/B07YFG3R5N",
    "supplier_link": "https://www.idealo.fr/prix/6938671/western-digital-red-sa500-1-to-2-5.html",
    "sas_link": "https://sas.selleramp.com/sas/lookup?SasLookup%5Bsearch_term%5D=B07YFG3R5N",
    "image_url": "https://m.media-amazon.com/images/I/31SjsttrKcL._SL120_.jpg",
    "posted": false,
    "posted_at": null,
    "created_at": "2026-07-23T06:41:41.065012+00:00"
  },
  {
    "ean": "0194850096761",
    "asin": "B08P1ZR2KZ",
    "name": "HP E24i G4",
    "supplier_cost": 231.324,
    "amazon_price": 466.15,
    "fees": 45.92,
    "profit": 188.90599999999995,
    "roi": 81.66294893742108,
    "estimated_sales": 35,
    "amazon_link": "https://www.amazon.fr/dp/B08P1ZR2KZ",
    "supplier_link": "https://www.idealo.fr/prix/201034156/hp-e24i-g4.html",
    "sas_link": "https://sas.selleramp.com/sas/lookup?SasLookup%5Bsearch_term%5D=B08P1ZR2KZ",
    "image_url": "https://m.media-amazon.com/images/I/41C2iYK2TfL._SL120_.jpg",
    "posted": false,
    "posted_at": null,
    "created_at": "2026-07-23T06:41:57.884632+00:00"
  },
  {
    "ean": "4711377279963",
    "asin": "B0BSLK4KNC",
    "name": "MSI Spatium M470 Pro",
    "supplier_cost": 102.71999999999998,
    "amazon_price": 196.83,
    "fees": 18.1,
    "profit": 76.01000000000003,
    "roi": 73.99727414330222,
    "estimated_sales": 71,
    "amazon_link": "https://www.amazon.fr/dp/B0BSLK4KNC",
    "supplier_link": "https://www.idealo.fr/prix/206184645/msi-spatium-m470-pro-1tb.html",
    "sas_link": "https://sas.selleramp.com/sas/lookup?SasLookup%5Bsearch_term%5D=B0BSLK4KNC",
    "image_url": "https://m.media-amazon.com/images/I/41bJbZDjayL._SL120_.jpg",
    "posted": false,
    "posted_at": null,
    "created_at": "2026-07-23T06:46:25.581385+00:00"
  },
  {
    "ean": "0840353906532",
    "asin": "B0D7TZCBC6",
    "name": "Google Pixel 9 Pro",
    "supplier_cost": 862.92,
    "amazon_price": 1173.88,
    "fees": 90.36,
    "profit": 220.60000000000025,
    "roi": 25.56436286098367,
    "estimated_sales": 35,
    "amazon_link": "https://www.amazon.fr/dp/B0D7TZCBC6",
    "supplier_link": "https://www.idealo.fr/prix/204671042/google-pixel-9-pro-512-go-vert-sauge.html",
    "sas_link": "https://sas.selleramp.com/sas/lookup?SasLookup%5Bsearch_term%5D=B0D7TZCBC6",
    "image_url": "https://m.media-amazon.com/images/I/21QmS3TMTkL._SL120_.jpg",
    "posted": false,
    "posted_at": null,
    "created_at": "2026-07-23T06:46:43.286443+00:00"
  },
  {
    "ean": "0760557861195",
    "asin": "B0BTDPXWPC",
    "name": "Transcend MTE300S",
    "supplier_cost": 53.364,
    "amazon_price": 113.52,
    "fees": 12.08,
    "profit": 48.076,
    "roi": 90.09069784873698,
    "estimated_sales": 14,
    "amazon_link": "https://www.amazon.fr/dp/B0BTDPXWPC",
    "supplier_link": "https://www.idealo.fr/prix/202321924/transcend-mte300s-256-go.html",
    "sas_link": "https://sas.selleramp.com/sas/lookup?SasLookup%5Bsearch_term%5D=B0BTDPXWPC",
    "image_url": "https://m.media-amazon.com/images/I/31IBVoRW-dL._SL120_.jpg",
    "posted": false,
    "posted_at": null,
    "created_at": "2026-07-23T06:47:03.992922+00:00"
  },
  {
    "ean": "0887111281470",
    "asin": "B0098NXDXG",
    "name": "HP C1Q10A",
    "supplier_cost": 114.49199999999999,
    "amazon_price": 263.16,
    "fees": 35.83,
    "profit": 112.83800000000005,
    "roi": 98.55535757956893,
    "estimated_sales": 59,
    "amazon_link": "https://www.amazon.fr/dp/B0098NXDXG",
    "supplier_link": "https://www.idealo.fr/prix/3736224/hp-c1q10a.html",
    "sas_link": "https://sas.selleramp.com/sas/lookup?SasLookup%5Bsearch_term%5D=B0098NXDXG",
    "image_url": "https://m.media-amazon.com/images/I/31zpgYaZFvL._SL120_.jpg",
    "posted": false,
    "posted_at": null,
    "created_at": "2026-07-23T06:47:28.636543+00:00"
  },
  {
    "ean": "6932554433345",
    "asin": "B0FY3W9QCG",
    "name": "Xiaomi Redmi Note 15 Pro Plus",
    "supplier_cost": 332.87999999999994,
    "amazon_price": 499.0,
    "fees": 42.06,
    "profit": 124.06000000000006,
    "roi": 37.268685412160565,
    "estimated_sales": 1253,
    "amazon_link": "https://www.amazon.fr/dp/B0FY3W9QCG",
    "supplier_link": "https://www.idealo.fr/prix/208749946/xiaomi-redmi-note-15-pro-plus-8-go-256-go-noir.html",
    "sas_link": "https://sas.selleramp.com/sas/lookup?SasLookup%5Bsearch_term%5D=B0FY3W9QCG",
    "image_url": "https://m.media-amazon.com/images/I/411DGF8sqoL._SL120_.jpg",
    "posted": false,
    "posted_at": null,
    "created_at": "2026-07-23T06:47:45.510849+00:00"
  },
  {
    "ean": "6932554435066",
    "asin": "B0FY3TMW4L",
    "name": "Xiaomi Redmi Note 15 Pro Plus",
    "supplier_cost": 332.87999999999994,
    "amazon_price": 499.0,
    "fees": 42.06,
    "profit": 124.06000000000006,
    "roi": 37.268685412160565,
    "estimated_sales": 1253,
    "amazon_link": "https://www.amazon.fr/dp/B0FY3TMW4L",
    "supplier_link": "https://www.idealo.fr/prix/208749941/xiaomi-redmi-note-15-pro-plus-8-go-256-moka.html",
    "sas_link": "https://sas.selleramp.com/sas/lookup?SasLookup%5Bsearch_term%5D=B0FY3TMW4L",
    "image_url": "https://m.media-amazon.com/images/I/415OagV3I6L._SL120_.jpg",
    "posted": false,
    "posted_at": null,
    "created_at": "2026-07-23T06:47:47.475790+00:00"
  },
  {
    "ean": "0718037891323",
    "asin": "B09H1CKTFP",
    "name": "Western Digital Red SN700",
    "supplier_cost": 105.972,
    "amazon_price": 299.99,
    "fees": 25.54,
    "profit": 168.478,
    "roi": 158.98350507681275,
    "estimated_sales": 87,
    "amazon_link": "https://www.amazon.fr/dp/B09H1CKTFP",
    "supplier_link": "https://www.idealo.fr/prix/201633414/western-digital-red-sn700-1-to.html",
    "sas_link": "https://sas.selleramp.com/sas/lookup?SasLookup%5Bsearch_term%5D=B09H1CKTFP",
    "image_url": "https://m.media-amazon.com/images/I/31FGW9+UkKL._SL120_.jpg",
    "posted": false,
    "posted_at": null,
    "created_at": "2026-07-23T06:47:51.817766+00:00"
  },
  {
    "ean": "0740617334890",
    "asin": "B0C4BJP2H8",
    "name": "Kingston DC600M",
    "supplier_cost": 540.0,
    "amazon_price": 1269.59,
    "fees": 96.03,
    "profit": 633.56,
    "roi": 117.32592592592593,
    "estimated_sales": 25,
    "amazon_link": "https://www.amazon.fr/dp/B0C4BJP2H8",
    "supplier_link": "https://www.idealo.fr/prix/202816468/kingston-dc600m-1-92-to.html",
    "sas_link": "https://sas.selleramp.com/sas/lookup?SasLookup%5Bsearch_term%5D=B0C4BJP2H8",
    "image_url": "https://m.media-amazon.com/images/I/31XFp4BvxiL._SL120_.jpg",
    "posted": false,
    "posted_at": null,
    "created_at": "2026-07-23T06:49:52.588612+00:00"
  },
  {
    "ean": "8885020620382",
    "asin": "B0D546B4LL",
    "name": "TP-Link Tapo C425 Solar KIT",
    "supplier_cost": 95.98799999999999,
    "amazon_price": 143.38,
    "fees": 17.76,
    "profit": 29.632000000000005,
    "roi": 30.87052548235197,
    "estimated_sales": 554,
    "amazon_link": "https://www.amazon.fr/dp/B0D546B4LL",
    "supplier_link": "https://www.idealo.fr/prix/204576290/tp-link-tapo-c425-solar-kit.html",
    "sas_link": "https://sas.selleramp.com/sas/lookup?SasLookup%5Bsearch_term%5D=B0D546B4LL",
    "image_url": "https://m.media-amazon.com/images/I/41tzWlWDdZL._SL120_.jpg",
    "posted": false,
    "posted_at": null,
    "created_at": "2026-07-23T06:50:01.262336+00:00"
  },
  {
    "ean": "4711377340960",
    "asin": "B096Y46DK1",
    "name": "MSI B840M Gaming Plus WiFi6E",
    "supplier_cost": 159.48,
    "amazon_price": 249.99,
    "fees": 25.28,
    "profit": 65.23000000000002,
    "roi": 40.90168046149989,
    "estimated_sales": 401,
    "amazon_link": "https://www.amazon.fr/dp/B096Y46DK1",
    "supplier_link": "https://www.idealo.fr/prix/206815144/msi-b840m-gaming-plus-wifi6e.html",
    "sas_link": "https://sas.selleramp.com/sas/lookup?SasLookup%5Bsearch_term%5D=B096Y46DK1",
    "image_url": "https://m.media-amazon.com/images/I/41S0BQMcriL._SL120_.jpg",
    "posted": false,
    "posted_at": null,
    "created_at": "2026-07-23T06:51:19.147605+00:00"
  }
]